canyonbpy/__init__.py
canyonbpy/core.py
canyonbpy/preprocessing.py
canyonbpy/utils.py
canyonbpy/data/__init__.py
canyonbpy/data/__pycache__/__init__.cpython-310.pyc
canyonbpy/data/__pycache__/__init__.cpython-38.pyc
canyonbpy/data/__pycache__/__init__.cpython-39.pyc
canyonbpy/data/weights/__init__.py
canyonbpy/data/weights/wgts_AT.txt
canyonbpy/data/weights/wgts_CT.txt
canyonbpy/data/weights/wgts_NO3.txt
canyonbpy/data/weights/wgts_PO4.txt
canyonbpy/data/weights/wgts_SiOH4.txt
canyonbpy/data/weights/wgts_pCO2.txt
canyonbpy/data/weights/wgts_pH.txt
canyonbpy/data/weights/__pycache__/__init__.cpython-310.pyc
canyonbpy/data/weights/__pycache__/__init__.cpython-38.pyc
canyonbpy/data/weights/__pycache__/__init__.cpython-39.pyc
canyonbpy-0.2.1.dist-info/LICENSE
canyonbpy-0.2.1.dist-info/METADATA
canyonbpy-0.2.1.dist-info/WHEEL
canyonbpy-0.2.1.dist-info/top_level.txt
canyonbpy-0.2.1.dist-info/RECORD
