Metadata-Version: 2.2
Name: canyonbpy
Version: 0.2.1
Summary: Python implementation of CANYON-B for oceanographic parameter predictions
Author-email: Raphaël Bajon <raphael.bajon@ifremer.fr>
License: MIT
Project-URL: Homepage, https://github.com/RaphaelBajon/canyonbpy
Project-URL: Bug Reports, https://github.com/RaphaelBajon/canyonbpy/issues
Project-URL: Source, https://github.com/RaphaelBajon/canyonbpy
Project-URL: Documentation, https://canyonbpy.readthedocs.io
Keywords: oceanography,CANYON-B,neural networks,carbon,nutrients
Classifier: Development Status :: 3 - Alpha
Classifier: Intended Audience :: Science/Research
Classifier: License :: OSI Approved :: MIT License
Classifier: Operating System :: OS Independent
Classifier: Programming Language :: Python :: 3
Classifier: Programming Language :: Python :: 3.7
Classifier: Programming Language :: Python :: 3.8
Classifier: Programming Language :: Python :: 3.9
Classifier: Programming Language :: Python :: 3.10
Classifier: Topic :: Scientific/Engineering :: Oceanography
Requires-Python: >=3.7
License-File: LICENSE
Requires-Dist: numpy>=1.20.0
Requires-Dist: xarray>=0.16.0
Requires-Dist: matplotlib>=3.3.0
Requires-Dist: PyCO2SYS>=1.8.0
Requires-Dist: pandas>=1.2.0
Requires-Dist: scipy>=1.6.0
